odoo/addons/document_page_portal/README.rst
odoo/addons/document_page_portal/__init__.py
odoo/addons/document_page_portal/__manifest__.py
odoo/addons/document_page_portal/controllers/__init__.py
odoo/addons/document_page_portal/controllers/portal.py
odoo/addons/document_page_portal/i18n/document_page_portal.pot
odoo/addons/document_page_portal/i18n/it.po
odoo/addons/document_page_portal/i18n/pt_BR.po
odoo/addons/document_page_portal/models/__init__.py
odoo/addons/document_page_portal/models/document_page.py
odoo/addons/document_page_portal/readme/CONFIGURE.rst
odoo/addons/document_page_portal/readme/CONTRIBUTORS.rst
odoo/addons/document_page_portal/readme/CREDITS.rst
odoo/addons/document_page_portal/readme/DESCRIPTION.rst
odoo/addons/document_page_portal/readme/USAGE.rst
odoo/addons/document_page_portal/security/document_page_portal_security.xml
odoo/addons/document_page_portal/security/ir.model.access.csv
odoo/addons/document_page_portal/static/description/banner.png
odoo/addons/document_page_portal/static/description/icon.png
odoo/addons/document_page_portal/static/description/index.html
odoo/addons/document_page_portal/static/src/js/document_page_portal_tour.js
odoo/addons/document_page_portal/tests/__init__.py
odoo/addons/document_page_portal/tests/test_document_page_portal.py
odoo/addons/document_page_portal/views/assets.xml
odoo/addons/document_page_portal/views/document_page.xml
odoo/addons/document_page_portal/views/document_page_portal_templates.xml
odoo13_addon_document_page_portal-13.0.1.0.1.dev8.dist-info/METADATA
odoo13_addon_document_page_portal-13.0.1.0.1.dev8.dist-info/WHEEL
odoo13_addon_document_page_portal-13.0.1.0.1.dev8.dist-info/top_level.txt
odoo13_addon_document_page_portal-13.0.1.0.1.dev8.dist-info/RECORD
