Metadata-Version: 2.1
Name: odoo13-addon-document_page_portal
Version: 13.0.1.0.1.dev8
Summary: This module enables document page portal
Home-page: https://github.com/OCA/knowledge
Author: Escodoo, Odoo Community Association (OCA)
Author-email: support@odoo-community.org
License: AGPL-3
Classifier: Programming Language :: Python
Classifier: Framework :: Odoo
Classifier: Framework :: Odoo :: 13.0
Classifier: License :: OSI Approved :: GNU Affero General Public License v3
Requires-Python: >=3.5
Requires-Dist: odoo13-addon-document-page
Requires-Dist: odoo<13.1dev,>=13.0a
